{
    "TZS": "TSh",
    "LRD": "$",
    "KHR": "\u17db",
    "LBP": "\u00a3",
    "ZAR": "R",
    "UYU": "$U",
    "ISK": "kr",
    "BBD": "$",
    "SAR": "\ufdfc",
    "RUB": "\u0440\u0443\u0431",
    "BTC": "BTC",
    "BOB": "$b",
    "CLP": "$",
    "SGD": "$",
    "DOP": "RD$",
    "JMD": "J$",
    "ANG": "\u0192",
    "NPR": "\u20a8",
    "YER": "\ufdfc",
    "SYP": "\u00a3",
    "OMR": "\ufdfc",
    "SRD": "$",
    "EGP": "\u00a3",
    "RON": "lei",
    "CUP": "$",
    "GBP": "\u00a3",
    "QAR": "\ufdfc",
    "USD": "$",
    "KGS": "\u043b\u0432",
    "BND": "$",
    "AWG": "\u0192",
    "BZD": "BZ$",
    "PLN": "z\u0142",
    "VND": "\u20ab",
    "NZD": "$",
    "KZT": "\u043b\u0432",
    "AZN": "\u043c\u0430\u043d",
    "TTD": "TT$",
    "HUF": "Ft",
    "LKR": "\u20a8",
    "NOK": "kr",
    "HRK": "kn",
    "LVL": "Ls",
    "SCR": "\u20a8",
    "PAB": "B/.",
    "CAD": "$",
    "UAH": "\u20b4",
    "CRC": "\u20a1",
    "BAM": "KM",
    "MXN": "$",
    "CZK": "K\u010d",
    "GYD": "$",
    "SEK": "kr",
    "ILS": "\u20aa",
    "FKP": "\u00a3",
    "ARS": "$",
    "MNT": "\u20ae",
    "MUR": "\u20a8",
    "RSD": "\u0414\u0438\u043d.",
    "BYR": "p.",
    "XCD": "$",
    "COP": "$",
    "BGN": "\u043b\u0432",
    "KPW": "\u20a9",
    "FJD": "$",
    "TWD": "NT$",
    "LAK": "\u20ad",
    "AFN": "\u060b",
    "IDR": "Rp",
    "GIP": "\u00a3",
    "KES": "KSh",
    "NIO": "C$",
    "CNY": "\u00a5",
    "PEN": "S/.",
    "HKD": "$",
    "KRW": "\u20a9",
    "THB": "\u0e3f",
    "SHP": "\u00a3",
    "DKK": "kr",
    "NAD": "$",
    "HNL": "L",
    "SBD": "$",
    "AUD": "$",
    "INR": "\u20b9",
    "IRR": "\ufdfc",
    "UGX": "USh",
    "GTQ": "Q",
    "JPY": "\u00a5",
    "SOS": "S",
    "EUR": "\u20ac",
    "NGN": "\u20a6",
    "UZS": "\u043b\u0432",
    "PKR": "\u20a8",
    "BWP": "P",
    "MKD": "\u0434\u0435\u043d",
    "KYD": "$",
    "PHP": "\u20b1",
    "BRL": "R$",
    "BSD": "$",
    "CHF": "Fr.",
    "PYG": "Gs",
    "ALL": "Lek",
    "MYR": "RM"
}